fwhunt_scan/__init__.py
fwhunt_scan/__init__.pyi
fwhunt_scan/py.typed
fwhunt_scan/test_internal.py
fwhunt_scan/uefi_analyzer.py
fwhunt_scan/uefi_analyzer.pyi
fwhunt_scan/uefi_extractor.py
fwhunt_scan/uefi_extractor.pyi
fwhunt_scan/uefi_protocols.py
fwhunt_scan/uefi_protocols.pyi
fwhunt_scan/uefi_scanner.py
fwhunt_scan/uefi_scanner.pyi
fwhunt_scan/uefi_smm.py
fwhunt_scan/uefi_smm.pyi
fwhunt_scan/uefi_tables.py
fwhunt_scan/uefi_tables.pyi
fwhunt_scan/uefi_te.py
fwhunt_scan/uefi_te.pyi
fwhunt_scan/uefi_types.py
fwhunt_scan/uefi_types.pyi
fwhunt_scan/uefi_utils.py
fwhunt_scan/uefi_utils.pyi
fwhunt_scan-2.3.5.data/scripts/fwhunt_scan_analyzer.py
fwhunt_scan-2.3.5.data/scripts/fwhunt_scan_docker.py
fwhunt_scan-2.3.5.dist-info/LICENSE
fwhunt_scan-2.3.5.dist-info/METADATA
fwhunt_scan-2.3.5.dist-info/WHEEL
fwhunt_scan-2.3.5.dist-info/top_level.txt
fwhunt_scan-2.3.5.dist-info/RECORD
