Metadata-Version: 2.1
Name: fwhunt-scan
Version: 2.3.5
Summary: Tools for analyzing UEFI firmware and checking UEFI modules with FwHunt rules
Home-page: https://github.com/binarly-io/fwhunt-scan
Author: FwHunt team
Author-email: fwhunt@binarly.io
License: GPL-3.0
Platform: Platform Independent
Classifier: Development Status :: 3 - Alpha
Classifier: License :: OSI Approved :: GNU General Public License v3 (GPLv3)
Classifier: Operating System :: OS Independent
Classifier: Programming Language :: Python :: 3
License-File: LICENSE
Requires-Dist: click >=7
Requires-Dist: rzpipe ==0.4.0
Requires-Dist: pyyaml ~=6.0.1
Requires-Dist: uefi-firmware >=1.10
Requires-Dist: shared-memory38 ; python_version >= "3.6" and python_version < "3.8"
